beanstalk_client/__init__.py
svknd_beanstalk_client-0.1.1.dist-info/LICENSE
svknd_beanstalk_client-0.1.1.dist-info/METADATA
svknd_beanstalk_client-0.1.1.dist-info/WHEEL
svknd_beanstalk_client-0.1.1.dist-info/top_level.txt
svknd_beanstalk_client-0.1.1.dist-info/RECORD
